{
    "color": {
        "name": "Pick Color",
        "controls": [
            {
                "type": "button",
                "icon": "bi bi-eyedropper",
                "label": "Pick Color"
            }
        ],
        "draggable": true
    },
    "deform": {
        "name": "Deform",
        "controls": [
            {
                "type": "button",
                "icon": "bi bi-droplet",
                "label": "Deform"
            }
        ],
        "draggable": true
    },
    "draw": {
        "name": "Draw",
        "controls": [
            {
                "type": "button",
                "icon": "bi bi-brush",
                "label": "Draw",
                "action": {
                    "type": "toolGroup",
                    "target": "draw"
                }
            }
        ],
        "draggable": true
    },
    "effects": {
        "name": "Effects",
        "controls": [
            {
                "type": "button",
                "icon": "bi bi-stars",
                "label": "Effects"
            }
        ],
        "draggable": true
    },
    "erase": {
        "name": "Erase",
        "controls": [
            {
                "type": "button",
                "icon": "bi bi-eraser",
                "label": "Erase"
            }
        ],
        "draggable": true
    },
    "history": {
        "name": "History",
        "controls": [
            {
                "type": "button",
                "icon": "bi bi-arrow-counterclockwise",
                "label": "Undo"
            },
            {
                "type": "button",
                "icon": "bi bi-arrow-clockwise",
                "label": "Redo"
            }
        ],
        "draggable": true
    },
    "layers": {
        "name": "Layers",
        "controls": [
            {
                "type": "button",
                "icon": "bi bi-layers",
                "label": "Layers"
            }
        ],
        "draggable": true
    },
    "search": {
        "name": "Search",
        "controls": [
            {
                "type": "button",
                "icon": "bi bi-search",
                "label": "Search",
                "expanded": true
            }
        ],
        "draggable": true
    },
    "selection": {
        "name": "Selection",
        "controls": [
            {
                "type": "button",
                "icon": "bi bi-bounding-box",
                "label": "Selection"
            }
        ],
        "draggable": true
    },
    "settings": {
        "name": "Settings",
        "controls": [
            {
                "type": "button",
                "icon": "bi bi-gear",
                "label": "Settings",
                "action": {
                    "type": "dock",
                    "target": "settings"
                }
            }
        ],
        "draggable": true
    },
    "text": {
        "name": "Text",
        "controls": [
            {
                "type": "button",
                "icon": "bi bi-type",
                "label": "Text"
            }
        ],
        "draggable": true
    },
    "transform": {
        "name": "Move / Transform",
        "controls": [
            {
                "type": "button",
                "icon": "bi bi-cursor",
                "label": "Move / Transform",
                "action": {
                    "type": "toolGroup",
                    "target": "transform"
                }
            }
        ],
        "draggable": true
    }
}